{
 "Account": { "Username": "xxxxxx",
              "Password": "xxxxxx"
              },

 "Interface":{ "Base Bet":"0.00005001",
               "Max Bet":"off",
               "Chance":"5",
               "Random":{"Auto": "on",
                         "Min" : "5",
                         "Max" : "15"
                        },

               "Cl_Seed":{"Auto"       :"on",
                          "Every_Lose" : "3"
                         }
              },

 "BetSet":{ "Bet"   : "L",
            "H / L" :{"Auto"   : "off",
                      "On Lose": "2",
                      "On Win" : "3"
                     }
          },

 "Increase" :{ "After Win"  : "1",
               "After Lose" : "1.2"
             },

 "Reset"    :{ "If_Win"   : "2",
               "If_Lose"  : "0"
             },

 "Stop"    :{ "Balance"  : "0.01",
              "If_Lose"  : "0",
              "If_Prof"  : "50000.01"
             },

 "Withdraw" :{"Auto"   : "OFF",
              "Initial": "0",
              "Trigger": "500000",
              "Wallet_doge" : "D7wnb429X7NYzmSA8Xy8WescWnj9dqG8mP",
              "Wallet_ltc" : "MFSk9QchuDoqDsz6Fj4VnLfrvi84nwSmJu",
              "Wallet_btc" : "3BAm1NZGbyQwG436JNTrXnJzVzxq1uXHzN",
              "Wallet_eth" : "0x1dba62e7348689fc726f00374456dbb33496b213"
              
             }
}
